tattletale.py
ntds_tattletale-3.1.0.dist-info/licenses/LICENSE
ntds_tattletale-3.1.0.dist-info/METADATA
ntds_tattletale-3.1.0.dist-info/WHEEL
ntds_tattletale-3.1.0.dist-info/entry_points.txt
ntds_tattletale-3.1.0.dist-info/top_level.txt
ntds_tattletale-3.1.0.dist-info/RECORD
