Metadata-Version: 2.4
Name: ntds-tattletale
Version: 3.1.0
Summary: Post-exploitation NTDS dump analyzer — correlates secretsdump output with hashcat potfiles to identify shared passwords and weak credentials in Active Directory
Author-email: Cory Avra <github@sillyrabbit.net>
License-Expression: MIT
Project-URL: Homepage, https://github.com/coryavra/tattletale
Project-URL: Repository, https://github.com/coryavra/tattletale
Project-URL: Issues, https://github.com/coryavra/tattletale/issues
Keywords: ntds,secretsdump,hashcat,potfile,active-directory,password-audit,penetration-testing,pentest,red-team,post-exploitation,credential-analysis,hash-cracking,security,infosec
Classifier: Development Status :: 5 - Production/Stable
Classifier: Environment :: Console
Classifier: Intended Audience :: Information Technology
Classifier: Intended Audience :: System Administrators
Classifier: Operating System :: OS Independent
Classifier: Programming Language :: Python :: 3
Classifier: Programming Language :: Python :: 3.10
Classifier: Programming Language :: Python :: 3.11
Classifier: Programming Language :: Python :: 3.12
Classifier: Programming Language :: Python :: 3.13
Classifier: Topic :: Security
Classifier: Topic :: System :: Systems Administration :: Authentication/Directory
Requires-Python: >=3.10
License-File: LICENSE
Dynamic: license-file
